<Defs>
	<ThingDef ParentName="ApparelMakeableBase">
    <defName>Yinglet_Matriarchal</defName>
    <label>Matriarch's Robes</label>
    <description>A set of clothes traditionally worn by the Matriarch of an enclave.</description>
		<graphicData>
			<texPath>Things/Pawn/YingPawn/Apparel/YingletLeaderClothes/Matriarch_YingFem_south</texPath>
			<graphicClass>Graphic_Single</graphicClass>
		</graphicData>
		<uiIconScale>1.3</uiIconScale>
		<techLevel>Neolithic</techLevel>
		<recipeMaker>
			<researchPrerequisite>ResearchProject_YingTribe</researchPrerequisite>
		</recipeMaker>
		<costStuffCount>35</costStuffCount>
		<stuffCategories>
			<li>Fabric</li>
			<li>Leathery</li>
		</stuffCategories>
		<thingCategories>
			<li>Apparel</li>
		</thingCategories>
		<statBases>
			<MaxHitPoints>100</MaxHitPoints>
			<WorkToMake>2700</WorkToMake>
			<Mass>0.25</Mass>
			<StuffEffectMultiplierArmor>0.2</StuffEffectMultiplierArmor>
			<StuffEffectMultiplierInsulation_Cold>0.22</StuffEffectMultiplierInsulation_Cold>
			<StuffEffectMultiplierInsulation_Heat>0.10</StuffEffectMultiplierInsulation_Heat>
			<EquipDelay>1.5</EquipDelay>
		</statBases>
		<apparel>
			<bodyPartGroups>
				<li>Torso</li>
				<li>Neck</li>
				<li>Shoulders</li>
				<li>Arms</li>
			</bodyPartGroups>
			<wornGraphicPath>Things/Pawn/YingPawn/Apparel/YingletLeaderClothes/Matriarch</wornGraphicPath>
			<layers>
				<li>Shell</li>
			</layers>
			<tags>
				<li>YingletFancy</li>
			</tags>
			<gender>Female</gender>
		</apparel>
	</ThingDef>	<ThingDef ParentName="ApparelMakeableBase">
    <defName>Yinglet_Patriarchal</defName>
    <label>Patriarch's Robes</label>
    <description>A set of clothes traditionally worn by the Patriarchs of an enclave.</description>
		<graphicData>
			<texPath>Things/Pawn/YingPawn/Apparel/YingletLeaderClothes/Patriarch_Ying_south</texPath>
			<graphicClass>Graphic_Single</graphicClass>
		</graphicData>
		<uiIconScale>1.3</uiIconScale>
		<techLevel>Neolithic</techLevel>
		<recipeMaker>
			<researchPrerequisite>ResearchProject_YingTribe</researchPrerequisite>
		</recipeMaker>
		<costStuffCount>35</costStuffCount>
		<stuffCategories>
			<li>Fabric</li>
			<li>Leathery</li>
		</stuffCategories>
		<thingCategories>
			<li>Apparel</li>
		</thingCategories>
		<statBases>
			<MaxHitPoints>100</MaxHitPoints>
			<WorkToMake>2700</WorkToMake>
			<Mass>0.25</Mass>
			<StuffEffectMultiplierArmor>0.2</StuffEffectMultiplierArmor>
			<StuffEffectMultiplierInsulation_Cold>0.22</StuffEffectMultiplierInsulation_Cold>
			<StuffEffectMultiplierInsulation_Heat>0.10</StuffEffectMultiplierInsulation_Heat>
			<EquipDelay>1.5</EquipDelay>
		</statBases>
		<apparel>
			<bodyPartGroups>
				<li>Torso</li>
				<li>Neck</li>
				<li>Shoulders</li>
				<li>Arms</li>
			</bodyPartGroups>
			<wornGraphicPath>Things/Pawn/YingPawn/Apparel/YingletLeaderClothes/Patriarch</wornGraphicPath>
			<layers>
				<li>Shell</li>
			</layers>
			<tags>
				<li>YingletFancy</li>
			</tags>
			<gender>Male</gender>
		</apparel>
	</ThingDef>
</Defs>
